README.md
setup.py
via_logger/__init__.py
via_logger/utils.py
via_logger.egg-info/PKG-INFO
via_logger.egg-info/SOURCES.txt
via_logger.egg-info/dependency_links.txt
via_logger.egg-info/requires.txt
via_logger.egg-info/top_level.txt